spectral_sound_analysis/__init__.py
spectral_sound_analysis/compile_metrics.py
spectral_sound_analysis/density.py
spectral_sound_analysis/init.py
spectral_sound_analysis/interface.py
spectral_sound_analysis/proc_audio.py
spectral_sound_analysis/spectral_power.py
spectral_sound_analysis/spectral_sound_analisys.py
spectral_sound_analysis-1.0.2.dist-info/LICENSE.txt
spectral_sound_analysis-1.0.2.dist-info/METADATA
spectral_sound_analysis-1.0.2.dist-info/WHEEL
spectral_sound_analysis-1.0.2.dist-info/top_level.txt
spectral_sound_analysis-1.0.2.dist-info/RECORD
