Metadata-Version: 2.1
Name: spectral_sound_analysis
Version: 1.0.2
Summary: A Python package for performing spectral analysis, audio signal processing, and related computations.
Home-page: https://github.com/LuisMRaimundo/Spectral_Sound_Analysis
Author: Luís Miguel da Luz Raimundo
Author-email: lmr.2020@outlook.pt
License: Creative Commons Attribution-NonCommercial-NoDerivatives 4.0 International License
Classifier: Programming Language :: Python :: 3
Classifier: Programming Language :: Python :: 3.8
Classifier: License :: Other/Proprietary License
Classifier: Operating System :: OS Independent
Requires-Python: >=3.8
License-File: LICENSE.txt
Requires-Dist: numpy>=1.18.0
Requires-Dist: scipy>=1.4.0
Requires-Dist: matplotlib>=3.2.0
Requires-Dist: pandas>=1.1.0
Requires-Dist: librosa>=0.8.0
Requires-Dist: PyQt5>=5.15.0
